LICENSE
MANIFEST.in
README.old
README.rst
README.txt
requirements.txt
setup.py
confined/__init__.py
confined/__main__.py
confined/check_arg.py
confined/test_check_arg.py
confined/test_valid.py
confined.egg-info/PKG-INFO
confined.egg-info/SOURCES.txt
confined.egg-info/dependency_links.txt
confined.egg-info/entry_points.txt
confined.egg-info/requires.txt
confined.egg-info/top_level.txt
scripts/confineds