Metadata-Version: 2.1
Name: confined
Version: 0.1.17
Summary: Safe Forth inspired templating language
Home-page: http://github.org/jul/confined
Author: Julien Tayon
Author-email: julien@tayon.net
License: License :: OSI Approved :: BSD License
Classifier: Development Status :: 4 - Beta
Classifier: Intended Audience :: Developers
Classifier: License :: OSI Approved :: Python Software Foundation License
Classifier: Programming Language :: Python :: 2.7
Classifier: Programming Language :: Python :: 3.9
Classifier: Operating System :: OS Independent
Classifier: Programming Language :: Python
License-File: LICENSE
Requires-Dist: prompt_toolkit
